{
  "status": "success",
  "bottleneck": "page_load\u2192upload_start",
  "action": "Landing page bounce",
  "configs_written": [
    "/home/runner/work/loopcanvas/loopcanvas/onboarding_config.json",
    "/home/runner/work/loopcanvas/loopcanvas/landing_config.json"
  ],
  "templates_written": [
    "/home/runner/work/loopcanvas/loopcanvas/templates/onboarding_tips.html",
    "/home/runner/work/loopcanvas/loopcanvas/templates/landing_hero_variant.html"
  ],
  "changes": {
    "show_upload_tip": true,
    "demo_mode_enabled": true,
    "mobile": {
      "enlarge_upload_button": true,
      "simplify_hero": true,
      "sticky_cta": true,
      "reduce_above_fold_content": true
    },
    "hero_variant": "social_proof",
    "cta_text": "Free Spotify Canvas \u2014 30 seconds",
    "show_demo_reel": true,
    "show_social_proof_above_fold": true
  },
  "metrics": {
    "stage_counts": {
      "page_load": 1,
      "upload_start": 0,
      "upload_complete": 0,
      "analyze_start": 0,
      "director_select": 0,
      "generate_start": 0,
      "generate_complete": 0,
      "export": 0
    },
    "stage_rates": {
      "page_load\u2192upload_start": 0.0,
      "upload_start\u2192upload_complete": 0.0,
      "upload_complete\u2192analyze_start": 0.0,
      "analyze_start\u2192director_select": 0.0,
      "director_select\u2192generate_start": 0.0,
      "generate_start\u2192generate_complete": 0.0,
      "generate_complete\u2192export": 0.0
    },
    "biggest_dropoff": "page_load\u2192upload_start",
    "biggest_dropoff_rate": 0.0,
    "overall_conversion": 0.0,
    "avg_time_to_export": 0.0,
    "bounce_rate": 1.0,
    "demo_conversion": 0.0,
    "mobile_ratio": 1.0,
    "mobile_bounce_rate": 1.0,
    "mobile_conversion": 0.0,
    "mobile_biggest_dropoff": "page_load\u2192upload_start",
    "mobile_biggest_dropoff_rate": 0.0
  },
  "reasoning": "Bottleneck: Landing page bounce (page_load\u2192upload_start, rate: 0%). Overall conversion: 0.0%. Bounce: 100%. Applied 7 config changes."
}
